<?xml version="1.0" encoding="UTF-8" standalone="yes"?>
<APIProxy revision="1" name="OnlyPost">
    <Basepaths>/onlypost</Basepaths>
    <ConfigurationVersion majorVersion="4" minorVersion="0"/>
    <CreatedAt>1519240467388</CreatedAt>
    <CreatedBy>sudheendras@google.com</CreatedBy>
    <Description></Description>
    <DisplayName>OnlyPost</DisplayName>
    <LastModifiedAt>1519240648405</LastModifiedAt>
    <LastModifiedBy>sudheendras@google.com</LastModifiedBy>
    <Policies>
        <Policy>Error</Policy>
    </Policies>
    <ProxyEndpoints>
        <ProxyEndpoint>default</ProxyEndpoint>
    </ProxyEndpoints>
    <Resources>
        <Resource>node://hello-world.js</Resource>
    </Resources>
    <Spec></Spec>
    <TargetServers/>
    <TargetEndpoints>
        <TargetEndpoint>default</TargetEndpoint>
    </TargetEndpoints>
    <validate>false</validate>
</APIProxy>
